LICENSE.txt
MANIFEST.in
README.md
pyproject.toml
setup.cfg
setup.py
src/falconify/__init__.py
src/falconify/config.json
src/falconify.egg-info/PKG-INFO
src/falconify.egg-info/SOURCES.txt
src/falconify.egg-info/dependency_links.txt
src/falconify.egg-info/entry_points.txt
src/falconify.egg-info/top_level.txt
src/falconify/Templates/CommandHandler.py.mako
src/falconify/Templates/Model.py.mako
src/falconify/Templates/Repository.py.mako
src/falconify/Templates/RequestHandler.py.mako
src/falconify/Templates/Routes.py.mako
src/falconify/Templates/Transformer.py.mako
src/falconify/Templates/UseCase.py.mako
src/falconify/Templates/__init__.py