Metadata-Version: 2.1
Name: falconify
Version: 0.1.1
Summary: The Scaffolding tool for Falconify
Home-page: https://gitlab.com/raphacosta/falconify-scaffolding
Author: Raphael Costa
Author-email: raphagc85@gmail.com
License: UNKNOWN
Project-URL: Bug Reports, https://gitlab.com/raphacosta/falconify-scaffolding/-/issues
Project-URL: Source, https://gitlab.com/raphacosta/falconify-scaffolding/
Keywords: falconify tooling development framework falcon
Platform: UNKNOWN
Classifier: Development Status :: 3 - Alpha
Classifier: Intended Audience :: Developers
Classifier: Topic :: Software Development :: Build Tools
Requires-Python: >=3.5, <4
